publicsuffix2/__init__.py
publicsuffix2/mpl-2.0.LICENSE
publicsuffix2/public_suffix_list.ABOUT
publicsuffix2/public_suffix_list.dat
publicsuffix2-2.20191219.dist-info/AUTHORS.rst
publicsuffix2-2.20191219.dist-info/METADATA
publicsuffix2-2.20191219.dist-info/WHEEL
publicsuffix2-2.20191219.dist-info/top_level.txt
publicsuffix2-2.20191219.dist-info/RECORD
