Metadata-Version: 2.1
Name: publicsuffix2
Version: 2.20191219
Summary: Get a public suffix for a domain name using the Public Suffix List. Forked from and using the same API as the publicsuffix package.
Home-page: https://github.com/nexb/python-publicsuffix2
Author: nexB Inc., Tomaz Solc, David Wilson and others.
Author-email: info@nexb.com
License: MIT and MPL-2.0
Keywords: domain,public suffix,suffix,dns,tld,sld,psl,idna
Platform: UNKNOWN
Classifier: Intended Audience :: Developers
Classifier: License :: OSI Approved :: MIT License
Classifier: License :: OSI Approved :: Mozilla Public License 2.0 (MPL 2.0)
Classifier: Programming Language :: Python
Classifier: Programming Language :: Python :: 2
Classifier: Programming Language :: Python :: 3
Classifier: Topic :: Internet :: Name Service (DNS)
Classifier: Topic :: Utilities
Classifier: Development Status :: 5 - Production/Stable
